odoo10_addon_account_invoice_view_payment-10.0.1.0.0-py2.7-nspkg.pth
odoo/addons/account_invoice_view_payment/README.rst
odoo/addons/account_invoice_view_payment/__init__.py
odoo/addons/account_invoice_view_payment/__manifest__.py
odoo/addons/account_invoice_view_payment/models/__init__.py
odoo/addons/account_invoice_view_payment/models/account_invoice.py
odoo/addons/account_invoice_view_payment/models/account_payment.py
odoo/addons/account_invoice_view_payment/static/description/icon.png
odoo/addons/account_invoice_view_payment/tests/__init__.py
odoo/addons/account_invoice_view_payment/tests/test_account_invoice_view_payment.py
odoo/addons/account_invoice_view_payment/views/account_invoice_view.xml
odoo/addons/account_invoice_view_payment/views/account_payment_view.xml
odoo/addons/account_invoice_view_payment/wizards/__init__.py
odoo/addons/account_invoice_view_payment/wizards/account_register_payments.py
odoo10_addon_account_invoice_view_payment-10.0.1.0.0.dist-info/DESCRIPTION.rst
odoo10_addon_account_invoice_view_payment-10.0.1.0.0.dist-info/METADATA
odoo10_addon_account_invoice_view_payment-10.0.1.0.0.dist-info/RECORD
odoo10_addon_account_invoice_view_payment-10.0.1.0.0.dist-info/WHEEL
odoo10_addon_account_invoice_view_payment-10.0.1.0.0.dist-info/metadata.json
odoo10_addon_account_invoice_view_payment-10.0.1.0.0.dist-info/namespace_packages.txt
odoo10_addon_account_invoice_view_payment-10.0.1.0.0.dist-info/top_level.txt
